{"cameraMode":{"drawMode":0,"name":"Shaded","section":"Shading Mode"},"sceneLighting":true,"audioPlay":false,"sceneViewState":{"m_AlwaysRefresh":false,"showFog":true,"showSkybox":true,"showFlares":true,"showImageEffects":true,"showParticleSystems":true,"showVisualEffectGraphs":true,"m_FxEnabled":true},"in2DMode":false,"pivot":{"x":149.91998291015626,"y":205.4091796875,"z":79.13468933105469},"rotation":{"x":-0.06326241791248322,"y":-0.012877102941274643,"z":0.0008164034225046635,"w":-0.9979166984558106},"size":368.80743408203127,"orthographic":false}